mutation_motif/__init__.py
mutation_motif/all_counts.py
mutation_motif/aln_to_counts.py
mutation_motif/cli.py
mutation_motif/complement.py
mutation_motif/draw.py
mutation_motif/entropy.py
mutation_motif/height.py
mutation_motif/log_lin.py
mutation_motif/motif_count.py
mutation_motif/mutation_analysis.py
mutation_motif/profile.py
mutation_motif/spectra_analysis.py
mutation_motif/util.py
mutation_motif/cfgs/grid.cfg
mutation_motif/cfgs/nbr.cfg
mutation_motif/cfgs/nbr_matrix.cfg
mutation_motif/cfgs/nbr_paths.cfg
mutation_motif/cfgs/spectra.cfg
mutation_motif-2025.7.17.dist-info/entry_points.txt
mutation_motif-2025.7.17.dist-info/licenses/license.txt
mutation_motif-2025.7.17.dist-info/WHEEL
mutation_motif-2025.7.17.dist-info/METADATA
mutation_motif-2025.7.17.dist-info/RECORD
