Metadata-Version: 2.4
Name: mutation_motif
Version: 2025.7.17
Summary: mutation_motif, software for analyses of point mutations, see https://www.ncbi.nlm.nih.gov/pubmed/27974498
Keywords: biology,genomics,statistics,genetics,evolution,bioinformatics,mutation
Author-email: Gavin Huttley <Gavin.Huttley@anu.edu.au>
Requires-Python: >=3.10,<3.14
Classifier: Development Status :: 5 - Production/Stable
Classifier: Intended Audience :: Science/Research
Classifier: License :: OSI Approved :: BSD License
Classifier: Topic :: Scientific/Engineering :: Bio-Informatics
Classifier: Topic :: Software Development :: Libraries :: Python Modules
Classifier: Operating System :: MacOS
Classifier: Operating System :: POSIX :: Linux
Classifier: Programming Language :: Python :: 3.10
Classifier: Programming Language :: Python :: 3.11
Classifier: Programming Language :: Python :: 3.12
Classifier: Programming Language :: Python :: 3.13
License-File: license.txt
Requires-Dist: click
Requires-Dist: cogent3>=2025.7.10a3
Requires-Dist: kaleido
Requires-Dist: numpy
Requires-Dist: scipy
Requires-Dist: scitrack
Requires-Dist: pandas
Requires-Dist: plotly
Requires-Dist: scipy
Requires-Dist: statsmodels
Requires-Dist: click ; extra == "dev"
Requires-Dist: cog ; extra == "dev"
Requires-Dist: flit ; extra == "dev"
Requires-Dist: pytest ; extra == "dev"
Requires-Dist: pytest-cov ; extra == "dev"
Requires-Dist: nox ; extra == "dev"
Requires-Dist: ruff ; extra == "dev"
Requires-Dist: pytest ; extra == "test"
Requires-Dist: pytest-cov ; extra == "test"
Requires-Dist: nox ; extra == "test"
Project-URL: Bug Tracker, https://github.com/HuttleyLab/MutationMotif/issues
Project-URL: Documentation, https://github.com/HuttleyLab/MutationMotif
Project-URL: Source Code, https://github.com/HuttleyLab/MutationMotif
Provides-Extra: dev
Provides-Extra: test
